lgwwhu/__init__.py
lgwwhu/main.py
lgwwhu-3.0.0.dist-info/LICENSE.txt
lgwwhu-3.0.0.dist-info/METADATA
lgwwhu-3.0.0.dist-info/WHEEL
lgwwhu-3.0.0.dist-info/entry_points.txt
lgwwhu-3.0.0.dist-info/top_level.txt
lgwwhu-3.0.0.dist-info/RECORD
