Metadata-Version: 2.1
Name: lgwwhu
Version: 3.0.0
Summary: Lensing gravitational waves
Home-page: 
Author: zrj
Author-email: 
Classifier: Programming Language :: Python :: 3
Classifier: License :: OSI Approved :: MIT License
Classifier: Operating System :: OS Independent
Requires-Python: >=3.6
License-File: LICENSE.txt
